becbacnet.py
becbacnet-0.0.4.dist-info/zip-safe
becbacnet-0.0.4.dist-info/DESCRIPTION.rst
becbacnet-0.0.4.dist-info/RECORD
becbacnet-0.0.4.dist-info/top_level.txt
becbacnet-0.0.4.dist-info/WHEEL
becbacnet-0.0.4.dist-info/METADATA
becbacnet-0.0.4.dist-info/metadata.json
