Metadata-Version: 2.0
Name: becbacnet
Version: 0.0.4
Summary: client for becbacnet API
Home-page: UNKNOWN
Author: Graeme Stuart
Author-email: ggstuart@gmail.com
License: UNKNOWN
Keywords: web services API
Platform: UNKNOWN
Classifier: Programming Language :: Python
Requires-Dist: requests
